vclip.py
vclip-0.1.1.dist-info/LICENSE.txt
vclip-0.1.1.dist-info/METADATA
vclip-0.1.1.dist-info/WHEEL
vclip-0.1.1.dist-info/entry_points.txt
vclip-0.1.1.dist-info/RECORD
