Metadata-Version: 2.1
Name: vclip
Version: 0.1.1
Summary: a small tool to compile randomly selected video clips from a folder of videos.
Home-page: https://github.com/jwyg/vclip
License: Anti-Capitalist Software License
Keywords: video
Author: Jonathan Gray
Author-email: contact@jonathangray.org
Requires-Python: >=3.8,<4.0
Classifier: License :: Other/Proprietary License
Classifier: Programming Language :: Python :: 3
Classifier: Programming Language :: Python :: 3.8
Classifier: Programming Language :: Python :: 3.9
Classifier: Programming Language :: Python :: 3.10
Classifier: Programming Language :: Python :: 3.11
Classifier: Programming Language :: Python :: 3.12
Requires-Dist: moviepy (>=1.0.3,<2.0.0)
Project-URL: Repository, https://github.com/jwyg/vclip
